README.rst
rpi_piusv.py
setup.py
rpi_piusv.egg-info/PKG-INFO
rpi_piusv.egg-info/SOURCES.txt
rpi_piusv.egg-info/dependency_links.txt
rpi_piusv.egg-info/not-zip-safe
rpi_piusv.egg-info/top_level.txt